{
  "generated_at": "2025-12-23T03:27:22.396930",
  "best_ticker": "TSLA",
  "directional_accuracy": 0.7166666666666667,
  "rmse": 0.061969433720531625,
  "mae": 0.04928307646857617,
  "r2": -0.7268725864126684,
  "feature_names": [
    "ema_diff_short",
    "ema_diff_long",
    "momentum5",
    "rsi14",
    "atr"
  ],
  "per_ticker_metrics": [
    {
      "ticker": "AAPL",
      "directional_accuracy": 0.6,
      "rmse": 0.026986754124055486,
      "mae": 0.02199380374002826,
      "r2": -0.07505770682973645
    },
    {
      "ticker": "MSFT",
      "directional_accuracy": 0.48333333333333334,
      "rmse": 0.029905481802009703,
      "mae": 0.023578924724565922,
      "r2": -0.1957127176228517
    },
    {
      "ticker": "AMZN",
      "directional_accuracy": 0.4166666666666667,
      "rmse": 0.05897742933683343,
      "mae": 0.0487690606241478,
      "r2": -0.7198173936482772
    },
    {
      "ticker": "META",
      "directional_accuracy": 0.6166666666666667,
      "rmse": 0.07279432568359961,
      "mae": 0.05320234171558702,
      "r2": -0.9422918332229611
    },
    {
      "ticker": "NVDA",
      "directional_accuracy": 0.5333333333333333,
      "rmse": 0.0671148794786864,
      "mae": 0.05458736561328924,
      "r2": -0.9934163144598009
    },
    {
      "ticker": "GOOGL",
      "directional_accuracy": 0.5666666666666667,
      "rmse": 0.051536065191698475,
      "mae": 0.044234847721569756,
      "r2": -0.37131144413318706
    },
    {
      "ticker": "TSLA",
      "directional_accuracy": 0.7166666666666667,
      "rmse": 0.061969433720531625,
      "mae": 0.04928307646857617,
      "r2": -0.7268725864126684
    },
    {
      "ticker": "NFLX",
      "directional_accuracy": 0.43333333333333335,
      "rmse": 0.06697299849428265,
      "mae": 0.05420922062044883,
      "r2": -1.0780245737602598
    },
    {
      "ticker": "ADBE",
      "directional_accuracy": 0.6833333333333333,
      "rmse": 0.04184065503571583,
      "mae": 0.032533222850782646,
      "r2": -0.21432736938382257
    }
  ],
  "model_artifact": "ml-models/trend_model.pkl"
}